xyppy/__init__.py
xyppy/blorb.py
xyppy/debug.py
xyppy/iff.py
xyppy/main.py
xyppy/ops.py
xyppy/ops_decode.py
xyppy/ops_impl.py
xyppy/ops_impl_compat.py
xyppy/quetzal.py
xyppy/six.py
xyppy/term.py
xyppy/vterm.py
xyppy/zenv.py
xyppy/zmath.py
xyfny-0.0.11.dist-info/LICENSE
xyfny-0.0.11.dist-info/METADATA
xyfny-0.0.11.dist-info/WHEEL
xyfny-0.0.11.dist-info/entry_points.txt
xyfny-0.0.11.dist-info/top_level.txt
xyfny-0.0.11.dist-info/RECORD
