Metadata-Version: 2.1
Name: xyfny
Version: 0.0.11
Summary: Reworking of xyppy
Home-page: https://github.com/jan-grant/xyfny
Author: theinternetftw, jang
Author-email: xyfny@ioctl.org
License: MIT License
Platform: UNKNOWN
Classifier: Development Status :: 4 - Beta
Classifier: Intended Audience :: Developers
Classifier: License :: OSI Approved :: MIT License
Classifier: Programming Language :: Python
Classifier: Programming Language :: Python :: 3
Classifier: Programming Language :: Python :: 3.6
Classifier: Programming Language :: Python :: 3.7
Classifier: Topic :: Games/Entertainment :: Puzzle Games
